Metadata-Version: 1.1
Name: office
Version: 0.0.1a0
Summary: No description yet
Home-page: https://github.com/ktr/office
Author: Kevin Ryan
Author-email: ktr@26ocb.com
License: MIT
Download-URL: https://github.com/ktr/office/archive/v0.0.1a0.tar.gz
Keywords: microsoft office outlook
Platform: UNKNOWN
Classifier: Development Status :: 3 - Alpha
Classifier: Intended Audience :: Developers
Classifier: Topic :: Office/Business
Classifier: Topic :: Software Development :: Libraries
Classifier: License :: OSI Approved :: MIT License
Classifier: Programming Language :: Python :: 3.6
Classifier: Programming Language :: Python :: 3.7
